biosets/__init__.py
biosets/__main__.py
biosets/arrow_dataset.py
biosets/config.py
biosets/data_files.py
biosets/dataset_dict.py
biosets/load.py
biosets/streaming.py
biosets/types.py
biosets/download/__init__.py
biosets/download/schema_manager.py
biosets/features/__init__.py
biosets/features/metadata.py
biosets/features/omics.py
biosets/features/targets.py
biosets/integration/__init__.py
biosets/integration/patcher.py
biosets/integration/datasets/__init__.py
biosets/integration/datasets/datasets.py
biosets/packaged_modules/__init__.py
biosets/packaged_modules/biodata/__init__.py
biosets/packaged_modules/biodata/biodata.py
biosets/packaged_modules/csv/__init__.py
biosets/packaged_modules/csv/csv.py
biosets/packaged_modules/genomics/__init__.py
biosets/packaged_modules/genomics/genomics.py
biosets/packaged_modules/genomics/snp.py
biosets/packaged_modules/metagenomics/__init__.py
biosets/packaged_modules/metagenomics/metagenomics.py
biosets/packaged_modules/metagenomics/otu.py
biosets/packaged_modules/npz/__init__.py
biosets/packaged_modules/npz/npz.py
biosets/packaged_modules/proteomics/__init__.py
biosets/packaged_modules/proteomics/maldi.py
biosets/packaged_modules/proteomics/proteomics.py
biosets/utils/__init__.py
biosets/utils/doc.py
biosets/utils/file_utils.py
biosets/utils/fingerprint.py
biosets/utils/generic.py
biosets/utils/gorilla.py
biosets/utils/logging.py
biosets/utils/naming.py
biosets/utils/py_util.py
biosets/utils/table_util.py
biosets/utils/version.py
biosets-1.2.1.dist-info/LICENSE
biosets-1.2.1.dist-info/METADATA
biosets-1.2.1.dist-info/WHEEL
biosets-1.2.1.dist-info/top_level.txt
biosets-1.2.1.dist-info/RECORD
