Metadata-Version: 2.1
Name: biosets
Version: 1.2.1
Summary: Bioinformatics datasets and tools
Home-page: https://github.com/psmyth94/biosets
Author: Patrick Smyth
Author-email: psmyth1994@gmail.com
License: Apache 2.0
Download-URL: https://github.com/psmyth94/biosets/tags
Keywords: omics machine learning bioinformatics datasets
Platform: UNKNOWN
Classifier: Development Status :: 5 - Production/Stable
Classifier: Intended Audience :: Developers
Classifier: Intended Audience :: Education
Classifier: Intended Audience :: Science/Research
Classifier: License :: OSI Approved :: Apache Software License
Classifier: Operating System :: OS Independent
Classifier: Programming Language :: Python :: 3
Classifier: Programming Language :: Python :: 3.8
Classifier: Programming Language :: Python :: 3.9
Classifier: Programming Language :: Python :: 3.10
Classifier: Programming Language :: Python :: 3.11
Classifier: Topic :: Scientific/Engineering :: Artificial Intelligence
Classifier: Topic :: Scientific/Engineering :: Bio-Informatics
Requires-Python: >=3.8.0,<3.12.0
Requires-Dist: datasets>=2.19.1
Requires-Dist: biocore
Provides-Extra: apache-beam
Requires-Dist: apache-beam<2.44.0,>=2.26.0; extra == "apache-beam"
Provides-Extra: docs
Requires-Dist: s3fs; extra == "docs"
Provides-Extra: jax
Requires-Dist: jax>=0.3.14; extra == "jax"
Requires-Dist: jaxlib>=0.3.14; extra == "jax"
Provides-Extra: polars
Requires-Dist: polars>=0.20.5; extra == "polars"
Requires-Dist: timezones>=0.10.2; extra == "polars"
Provides-Extra: quality
Requires-Dist: ruff>=0.1.5; extra == "quality"
Provides-Extra: s3
Requires-Dist: s3fs; extra == "s3"
Provides-Extra: scipy
Requires-Dist: scipy; extra == "scipy"
Provides-Extra: tensorflow
Requires-Dist: tensorflow!=2.6.0,!=2.6.1,>=2.2.0; (sys_platform != "darwin" or platform_machine != "arm64") and extra == "tensorflow"
Requires-Dist: tensorflow-macos; (sys_platform == "darwin" and platform_machine == "arm64") and extra == "tensorflow"
Provides-Extra: tensorflow_gpu
Requires-Dist: tensorflow-gpu!=2.6.0,!=2.6.1,>=2.2.0; extra == "tensorflow-gpu"
Provides-Extra: test
Requires-Dist: ruff>=0.1.5; extra == "test"
Requires-Dist: pytest; extra == "test"
Requires-Dist: pytest-timeout; extra == "test"
Requires-Dist: pytest-xdist; extra == "test"
Requires-Dist: scipy; extra == "test"
Requires-Dist: polars>=0.20.5; extra == "test"
Requires-Dist: timezones>=0.10.2; extra == "test"
Requires-Dist: s3fs; extra == "test"
Provides-Extra: torch
Requires-Dist: torch; extra == "torch"
Provides-Extra: vcf
Requires-Dist: cyvcf2>=0.30.0; extra == "vcf"
Requires-Dist: sgkit>=0.0.1; extra == "vcf"
